pytest_peach.py
pytest_peach-1.5.41.dist-info/LICENSE
pytest_peach-1.5.41.dist-info/METADATA
pytest_peach-1.5.41.dist-info/WHEEL
pytest_peach-1.5.41.dist-info/entry_points.txt
pytest_peach-1.5.41.dist-info/top_level.txt
pytest_peach-1.5.41.dist-info/RECORD
