Metadata-Version: 2.1
Name: pytest-peach
Version: 1.5.41
Summary: pytest plugin for fuzzing with Peach API Security
Home-page: https://peach.tech
Author: Peach Tech
Author-email: contact@peachfuzzer.com
License: Apache License, Version 2.0
Keywords: py.test pytest fuzzing peach
Platform: UNKNOWN
Classifier: Development Status :: 4 - Beta
Classifier: Framework :: Pytest
Classifier: Intended Audience :: Developers
Classifier: License :: OSI Approved :: Apache Software License
Classifier: Operating System :: POSIX
Classifier: Operating System :: Microsoft :: Windows
Classifier: Operating System :: MacOS :: MacOS X
Classifier: Topic :: Security
Classifier: Topic :: Software Development :: Quality Assurance
Classifier: Topic :: Software Development :: Testing
Classifier: Topic :: Utilities
Classifier: Programming Language :: Python
Classifier: Programming Language :: Python :: 2.6
Classifier: Programming Language :: Python :: 2.7
Classifier: Programming Language :: Python :: 3.2
Classifier: Programming Language :: Python :: 3.3
Classifier: Programming Language :: Python :: 3.4
Classifier: Programming Language :: Python :: 3.5
Requires-Dist: pytest (>=2.8.7)
Requires-Dist: peachapisec-api (>=1.5.41)
